{
  "collectionName": "components_client_info_components_client_info_components",
  "info": {
    "name": "ClientInfoComponent",
    "icon": "address-card"
  },
  "options": {},
  "attributes": {
    "name": {
      "type": "string"
    },
    "url": {
      "type": "string"
    },
    "logo": {
      "model": "file",
      "via": "related",
      "allowedTypes": [
        "images",
        "files",
        "videos"
      ],
      "plugin": "upload",
      "required": false
    },
    "designs": {
      "collection": "design"
    }
  }
}
